tt_playing_cards/__init__.py
tt_playing_cards/abstract.py
tt_playing_cards/hanabi_cards.py
tt_playing_cards/playing_cards.py
tt_playing_cards/test_abstract.py
tt_playing_cards/test_hanabi_cards.py
playing_cards_tylertrussell-0.dev4.dist-info/LICENSE
playing_cards_tylertrussell-0.dev4.dist-info/METADATA
playing_cards_tylertrussell-0.dev4.dist-info/WHEEL
playing_cards_tylertrussell-0.dev4.dist-info/top_level.txt
playing_cards_tylertrussell-0.dev4.dist-info/RECORD
