Metadata-Version: 2.1
Name: playing-cards-tylertrussell
Version: 0.dev4
Summary: Basic playing cards
Home-page: https://www.github.com/tylertrussell/hanabi-cards
Author: Tyler Trussell
Author-email: tigertrussell+pypi@gmail.com
Requires-Python: >=3.9
License-File: LICENSE
